download-util/__init__.py
download-util/download_util.py
download_util/__init__.py
download_util/download_util.py
download_novel_util-0.0.1.dist-info/LICENSE
download_novel_util-0.0.1.dist-info/METADATA
download_novel_util-0.0.1.dist-info/WHEEL
download_novel_util-0.0.1.dist-info/top_level.txt
download_novel_util-0.0.1.dist-info/RECORD
